{
    "channels": {
        "ch1": {
            "operations": {
                "half_max_square": {
                    "length": 16,
                    "amplitude": 0.25,
                    "__class__": "quam.components.pulses.SquarePulse"
                }
            },
            "sticky": {
                "duration": 1000,
                "digital": false,
                "__class__": "quam.components.channels.StickyChannelAddon"
            },
            "opx_output": [
                "con1",
                1
            ],
            "__class__": "quam.components.channels.SingleChannel"
        },
        "ch2": {
            "operations": {
                "half_max_square": {
                    "length": 16,
                    "amplitude": 0.25,
                    "__class__": "quam.components.pulses.SquarePulse"
                }
            },
            "sticky": {
                "duration": 1000,
                "digital": false,
                "__class__": "quam.components.channels.StickyChannelAddon"
            },
            "opx_output": [
                "con1",
                2
            ],
            "__class__": "quam.components.channels.SingleChannel"
        },
        "ch1_readout": {
            "operations": {
                "readout": {
                    "length": 1500,
                    "id": "readout",
                    "amplitude": 0.01,
                    "__class__": "quam.components.pulses.SquareReadoutPulse"
                },
                "half_max_square": {
                    "length": 16,
                    "amplitude": 0.25,
                    "__class__": "quam.components.pulses.SquarePulse"
                }
            },
            "sticky": {
                "duration": 1000,
                "digital": false,
                "__class__": "quam.components.channels.StickyChannelAddon"
            },
            "intermediate_frequency": 13333333,
            "opx_input": [
                "con1",
                1
            ],
            "opx_output": [
                "con1",
                3
            ],
            "__class__": "quam.components.channels.InOutSingleChannel"
        },
        "ch2_readout": {
            "operations": {
                "readout": {
                    "length": 1500,
                    "id": "readout",
                    "amplitude": 0.01,
                    "__class__": "quam.components.pulses.SquareReadoutPulse"
                }
            },
            "sticky": {
                "duration": 1000,
                "digital": false,
                "__class__": "quam.components.channels.StickyChannelAddon"
            },
            "intermediate_frequency": 23333333,
            "opx_input": [
                "con1",
                1
            ],
            "opx_output": [
                "con1",
                3
            ],
            "__class__": "quam.components.channels.InOutSingleChannel"
        },
        "ch3_readout": {
            "operations": {
                "readout": {
                    "length": 1500,
                    "id": "readout",
                    "amplitude": 0.01,
                    "__class__": "quam.components.pulses.SquareReadoutPulse"
                }
            },
            "sticky": {
                "duration": 1000,
                "digital": false,
                "__class__": "quam.components.channels.StickyChannelAddon"
            },
            "intermediate_frequency": 33333333,
            "opx_input": [
                "con1",
                1
            ],
            "opx_output": [
                "con1",
                3
            ],
            "__class__": "quam.components.channels.InOutSingleChannel"
        },
        "ch4_readout": {
            "operations": {
                "readout": {
                    "length": 1500,
                    "id": "readout",
                    "amplitude": 0.01,
                    "__class__": "quam.components.pulses.SquareReadoutPulse"
                }
            },
            "sticky": {
                "duration": 1000,
                "digital": false,
                "__class__": "quam.components.channels.StickyChannelAddon"
            },
            "intermediate_frequency": 43333333,
            "opx_input": [
                "con1",
                1
            ],
            "opx_output": [
                "con1",
                3
            ],
            "__class__": "quam.components.channels.InOutSingleChannel"
        },
        "ch5_readout": {
            "operations": {
                "readout": {
                    "length": 1500,
                    "id": "readout",
                    "amplitude": 0.01,
                    "__class__": "quam.components.pulses.SquareReadoutPulse"
                }
            },
            "sticky": {
                "duration": 1000,
                "digital": false,
                "__class__": "quam.components.channels.StickyChannelAddon"
            },
            "intermediate_frequency": 53333333,
            "opx_input": [
                "con1",
                1
            ],
            "opx_output": [
                "con1",
                3
            ],
            "__class__": "quam.components.channels.InOutSingleChannel"
        },
        "ch6_readout": {
            "operations": {
                "readout": {
                    "length": 1500,
                    "id": "readout",
                    "amplitude": 0.01,
                    "__class__": "quam.components.pulses.SquareReadoutPulse"
                }
            },
            "sticky": {
                "duration": 1000,
                "digital": false,
                "__class__": "quam.components.channels.StickyChannelAddon"
            },
            "intermediate_frequency": 63333333,
            "opx_input": [
                "con1",
                1
            ],
            "opx_output": [
                "con1",
                3
            ],
            "__class__": "quam.components.channels.InOutSingleChannel"
        }
    },
    "__class__": "quam.components.basic_quam.BasicQuam"
}